pytest_snail/__init__.py
pytest_snail/plugin.py
pytest_snail-0.1.0.dist-info/LICENSE
pytest_snail-0.1.0.dist-info/METADATA
pytest_snail-0.1.0.dist-info/WHEEL
pytest_snail-0.1.0.dist-info/entry_points.txt
pytest_snail-0.1.0.dist-info/top_level.txt
pytest_snail-0.1.0.dist-info/RECORD
