Metadata-Version: 2.1
Name: pytest-snail
Version: 0.1.0
Summary: Plugin for adding a marker to slow running tests. 🐌
Home-page: https://github.com/hackebrot/pytest-snail
Author: Raphael Pierzina
Author-email: raphael@hackebrot.de
Maintainer: Raphael Pierzina
Maintainer-email: raphael@hackebrot.de
License: MIT License
Project-URL: Repository, https://github.com/hackebrot/pytest-snail
Project-URL: Issues, https://github.com/hackebrot/pytest-snail/issues
Keywords: pytest
Platform: UNKNOWN
Classifier: Development Status :: 3 - Alpha
Classifier: Framework :: Pytest
Classifier: Intended Audience :: Developers
Classifier: Topic :: Software Development :: Testing
Classifier: Programming Language :: Python
Classifier: Programming Language :: Python :: 3 :: Only
Classifier: Programming Language :: Python :: 3.6
Classifier: Programming Language :: Python :: 3.7
Classifier: Operating System :: OS Independent
Classifier: License :: OSI Approved :: MIT License
Requires-Python: >=3.6
Requires-Dist: pytest (>=5.0.1)
